{
  "schemaVersion": 1,
  "workspace": "sdkwork-portal-app-sdk",
  "sdkOwner": "sdkwork-portal",
  "apiAuthority": "sdkwork-portal-app-api",
  "sourceAuthoritySpec": "../../apis/app-api/portal/portal-app-api.openapi.json",
  "authoritySpec": "openapi/sdkwork-portal-app-api.openapi.json",
  "generationInputSpec": "openapi/sdkwork-portal-app-api.sdkgen.json",
  "derivedSpecs": {
    "default": "openapi/sdkwork-portal-app-api.sdkgen.json"
  },
  "discoverySurface": {
    "sdkTarget": "app",
    "apiPrefix": "/app/v3/api",
    "generatedProtocols": [
      "http-openapi"
    ],
    "manualTransports": []
  },
  "languages": [
    {
      "language": "typescript",
      "workspace": "sdkwork-portal-app-sdk-typescript",
      "generationState": "declared",
      "releaseState": "not_published",
      "generatedPath": "sdkwork-portal-app-sdk-typescript/generated/server-openapi",
      "name": "@sdkwork/sdkwork-portal-app-sdk",
      "version": "0.1.0"
    }
  ],
  "sdkDependencies": []
}
